README.rst
setup.py
django_isckea_models/__init__.py
django_isckea_models/models.py
django_isckea_models.egg-info/PKG-INFO
django_isckea_models.egg-info/SOURCES.txt
django_isckea_models.egg-info/dependency_links.txt
django_isckea_models.egg-info/requires.txt
django_isckea_models.egg-info/top_level.txt