Metadata-Version: 1.1
Name: django-isckea-models
Version: 1.0
Summary: ISC Kea models for Django
Home-page: https://bitbucket.org/code-orange/django-isckea-models/
Author: Kevin Olbrich
Author-email: ko@sv01.de
License: LGPL version 3 or later
Download-URL: https://bitbucket.org/code-orange/django-isckea-models/downloads/
Platform: any
Classifier: Development Status :: 5 - Production/Stable
Classifier: Framework :: Django
Classifier: Intended Audience :: Developers
Classifier: Intended Audience :: System Administrators
Classifier: License :: OSI Approved :: GNU Lesser General Public License v3 or later (LGPLv3+)
Classifier: Operating System :: OS Independent
Classifier: Programming Language :: Python
Classifier: Topic :: Internet :: WWW/HTTP :: WSGI :: Application
Classifier: Topic :: Software Development :: Libraries :: Python Modules
